mcpyrate-3.6.4.dist-info/METADATA
mcpyrate-3.6.4.dist-info/WHEEL
mcpyrate-3.6.4.dist-info/entry_points.txt
mcpyrate-3.6.4.dist-info/licenses/LICENSE
mcpyrate/.mypy_cache/.gitignore
mcpyrate/.mypy_cache/3.8/@plugins_snapshot.json
mcpyrate/.mypy_cache/3.8/_ast.data.json
mcpyrate/.mypy_cache/3.8/_ast.meta.json
mcpyrate/.mypy_cache/3.8/_importlib_modulespec.data.json
mcpyrate/.mypy_cache/3.8/_importlib_modulespec.meta.json
mcpyrate/.mypy_cache/3.8/_typeshed/__init__.data.json
mcpyrate/.mypy_cache/3.8/_typeshed/__init__.meta.json
mcpyrate/.mypy_cache/3.8/_warnings.data.json
mcpyrate/.mypy_cache/3.8/_warnings.meta.json
mcpyrate/.mypy_cache/3.8/abc.data.json
mcpyrate/.mypy_cache/3.8/abc.meta.json
mcpyrate/.mypy_cache/3.8/array.data.json
mcpyrate/.mypy_cache/3.8/array.meta.json
mcpyrate/.mypy_cache/3.8/ast.data.json
mcpyrate/.mypy_cache/3.8/ast.meta.json
mcpyrate/.mypy_cache/3.8/builtins.data.json
mcpyrate/.mypy_cache/3.8/builtins.meta.json
mcpyrate/.mypy_cache/3.8/codecs.data.json
mcpyrate/.mypy_cache/3.8/codecs.meta.json
mcpyrate/.mypy_cache/3.8/collections/__init__.data.json
mcpyrate/.mypy_cache/3.8/collections/__init__.meta.json
mcpyrate/.mypy_cache/3.8/collections/abc.data.json
mcpyrate/.mypy_cache/3.8/collections/abc.meta.json
mcpyrate/.mypy_cache/3.8/contextlib.data.json
mcpyrate/.mypy_cache/3.8/contextlib.meta.json
mcpyrate/.mypy_cache/3.8/copy.data.json
mcpyrate/.mypy_cache/3.8/copy.meta.json
mcpyrate/.mypy_cache/3.8/distutils/__init__.data.json
mcpyrate/.mypy_cache/3.8/distutils/__init__.meta.json
mcpyrate/.mypy_cache/3.8/distutils/ccompiler.data.json
mcpyrate/.mypy_cache/3.8/distutils/ccompiler.meta.json
mcpyrate/.mypy_cache/3.8/distutils/sysconfig.data.json
mcpyrate/.mypy_cache/3.8/distutils/sysconfig.meta.json
mcpyrate/.mypy_cache/3.8/enum.data.json
mcpyrate/.mypy_cache/3.8/enum.meta.json
mcpyrate/.mypy_cache/3.8/functools.data.json
mcpyrate/.mypy_cache/3.8/functools.meta.json
mcpyrate/.mypy_cache/3.8/genericpath.data.json
mcpyrate/.mypy_cache/3.8/genericpath.meta.json
mcpyrate/.mypy_cache/3.8/importlib/__init__.data.json
mcpyrate/.mypy_cache/3.8/importlib/__init__.meta.json
mcpyrate-3.6.4.dist-info/RECORD
