Metadata-Version: 2.1
Name: mcpyrate
Version: 3.6.4
Summary: Advanced macro expander and language lab for Python
Keywords: macros,syntactic-macros,macro-expander,metaprogramming,import,importer
Author: Salvador de la Puente González
Author-Email: Juha Jeronen <juha.m.jeronen@gmail.com>
License: MIT
Classifier: Development Status :: 4 - Beta
Classifier: Environment :: Other Environment
Classifier: Intended Audience :: Developers
Classifier: License :: OSI Approved :: MIT License
Classifier: Operating System :: OS Independent
Classifier: Programming Language :: Python
Classifier: Programming Language :: Python :: 3 :: Only
Classifier: Programming Language :: Python :: 3.8
Classifier: Programming Language :: Python :: 3.9
Classifier: Programming Language :: Python :: 3.10
Classifier: Programming Language :: Python :: 3.11
Classifier: Programming Language :: Python :: 3.12
Classifier: Programming Language :: Python :: Implementation :: CPython
Classifier: Programming Language :: Python :: Implementation :: PyPy
Classifier: Topic :: Software Development :: Libraries
Classifier: Topic :: Software Development :: Libraries :: Python Modules
Classifier: Topic :: Software Development :: Code Generators
Classifier: Topic :: Utilities
Project-URL: Repository, https://github.com/Technologicat/mcpyrate
Requires-Python: >=3.8
Requires-Dist: colorama>=0.4.4
